endstone_bstats/__init__.py
endstone_bstats/_base.py
endstone_bstats/_config.py
endstone_bstats/_errors.py
endstone_bstats/_executor.py
endstone_bstats/_metrics.py
endstone_bstats/_charts/__init__.py
endstone_bstats/_charts/advanced_bar_chart.py
endstone_bstats/_charts/advanced_pie.py
endstone_bstats/_charts/custom_chart.py
endstone_bstats/_charts/drilldown_pie.py
endstone_bstats/_charts/multi_line_chart.py
endstone_bstats/_charts/simple_bar_chart.py
endstone_bstats/_charts/simple_pie.py
endstone_bstats/_charts/single_line_chart.py
endstone_bstats-0.1.0.dist-info/METADATA
endstone_bstats-0.1.0.dist-info/WHEEL
endstone_bstats-0.1.0.dist-info/licenses/LICENSE
endstone_bstats-0.1.0.dist-info/RECORD
